cgiproxy/__init__.py
cgiproxy-20.11.14.dist-info/LICENSE
cgiproxy-20.11.14.dist-info/METADATA
cgiproxy-20.11.14.dist-info/WHEEL
cgiproxy-20.11.14.dist-info/top_level.txt
cgiproxy-20.11.14.dist-info/RECORD
