Metadata-Version: 2.1
Name: cgiproxy
Version: 20.11.14
Summary: The simple HTTP proxy.
Home-page: https://github.com/Datamart/CGI-Proxy
Author: Valentin Podkamennyi, Alex Krailo
License: Apache 2.0
Platform: UNKNOWN
Classifier: Development Status :: 5 - Production/Stable
Classifier: Intended Audience :: Developers
Classifier: Programming Language :: Python
Classifier: Programming Language :: Python :: 2
Classifier: Programming Language :: Python :: 3
Classifier: License :: OSI Approved :: Apache Software License
Classifier: Topic :: Software Development :: Libraries :: Python Modules
